fulfulde_stopwords/__init__.py
fulfulde_stopwords/core.py
fulfulde_stopwords/stopwords.txt
fulfulde_stopwords-1.0.dist-info/licenses/LICENSE
fulfulde_stopwords-1.0.dist-info/METADATA
fulfulde_stopwords-1.0.dist-info/WHEEL
fulfulde_stopwords-1.0.dist-info/top_level.txt
fulfulde_stopwords-1.0.dist-info/RECORD
