Metadata-Version: 2.4
Name: fulfulde-stopwords
Version: 1.0
Summary: Stopwords for the Fulfulde language (Adamawa variant)
Home-page: https://github.com/2zalab/fulfulde-stopwords
Author: Research Team
Author-email: Isaac Touza <isaac.touza@univ-maroua.cm>
Maintainer-email: Isaac Touza <isaac.touza@univ-maroua.cm>
License: MIT
Project-URL: Homepage, https://github.com/2zalab/fulfulde-stopwords
Project-URL: Documentation, https://github.com/2zalab/fulfulde-stopwords#readme
Project-URL: Repository, https://github.com/2zalab/fulfulde-stopwords
Project-URL: Bug Tracker, https://github.com/2zalab/fulfulde-stopwords/issues
Keywords: nlp,natural-language-processing,stopwords,fulfulde,african-languages,low-resource-languages,text-processing,computational-linguistics
Classifier: Development Status :: 4 - Beta
Classifier: Intended Audience :: Developers
Classifier: Intended Audience :: Science/Research
Classifier: License :: OSI Approved :: MIT License
Classifier: Natural Language :: English
Classifier: Operating System :: OS Independent
Classifier: Programming Language :: Python :: 3
Classifier: Programming Language :: Python :: 3.7
Classifier: Programming Language :: Python :: 3.8
Classifier: Programming Language :: Python :: 3.9
Classifier: Programming Language :: Python :: 3.10
Classifier: Programming Language :: Python :: 3.11
Classifier: Programming Language :: Python :: 3.12
Classifier: Topic :: Scientific/Engineering :: Artificial Intelligence
Classifier: Topic :: Text Processing :: Linguistic
Classifier: Topic :: Software Development :: Libraries :: Python Modules
Requires-Python: >=3.7
License-File: LICENSE
Provides-Extra: dev
Requires-Dist: pytest>=7.0.0; extra == "dev"
Requires-Dist: pytest-cov>=4.0.0; extra == "dev"
Requires-Dist: black>=22.0.0; extra == "dev"
Requires-Dist: flake8>=5.0.0; extra == "dev"
Requires-Dist: mypy>=0.990; extra == "dev"
Dynamic: author
Dynamic: home-page
Dynamic: license-file
Dynamic: requires-python
